wolves_python/__init__.py
wolves_python/client.py
wolves_python/event_logger.py
wolves_python/experiment.py
wolves_python/future.py
wolves_python/metadata.py
wolves_python/network.py
wolves_python/runtime.py
wolves_python/store.py
wolves_python/types.py
wolves_python-1.0.4.dist-info/METADATA
wolves_python-1.0.4.dist-info/WHEEL
wolves_python-1.0.4.dist-info/top_level.txt
wolves_python-1.0.4.dist-info/RECORD
