Metadata-Version: 2.4
Name: wolves-python
Version: 1.0.4
Summary: Wolves Python SDK
Requires-Python: >=3.10
Requires-Dist: httpx>=0.25.0
Provides-Extra: dev
Requires-Dist: pytest>=7.0.0; extra == "dev"
Requires-Dist: pytest-cov>=4.0.0; extra == "dev"
Requires-Dist: coverage>=7.0.0; extra == "dev"
Requires-Dist: respx>=0.21.0; extra == "dev"
